mergecat/__init__.py
mergecat/__main__.py
mergecat-0.0.7.dist-info/LICENSE
mergecat-0.0.7.dist-info/METADATA
mergecat-0.0.7.dist-info/WHEEL
mergecat-0.0.7.dist-info/entry_points.txt
mergecat-0.0.7.dist-info/top_level.txt
mergecat-0.0.7.dist-info/RECORD
