Metadata-Version: 2.1
Name: mergecat
Version: 0.0.7
Summary: Automatic voice line clip extractor
Home-page: https://github.com/yttrian/mergecat
Author: Ian Moore
Author-email: mergecat@yttr.org
License: UNKNOWN
Platform: UNKNOWN
Classifier: Programming Language :: Python :: 3
Classifier: License :: OSI Approved :: MIT License
Classifier: Operating System :: OS Independent
Requires-Python: >=3.6
Requires-Dist: click
